transitions_anyio/__init__.py
transitions_anyio-0.3.0.dist-info/LICENSE
transitions_anyio-0.3.0.dist-info/WHEEL
transitions_anyio-0.3.0.dist-info/METADATA
transitions_anyio-0.3.0.dist-info/RECORD
