Metadata-Version: 2.1
Name: transitions-anyio
Version: 0.3.0
Summary: An extension for the transitions state machine library which runs asynchronous state machines using anyio.
License: MIT
Author: Alexander Neumann
Author-email: aleneum@gmail.com
Maintainer: Omer Katz
Maintainer-email: omer.drow@gmail.com
Requires-Python: >=3.7.1,<4.0.0
Classifier: License :: OSI Approved :: MIT License
Classifier: Programming Language :: Python :: 3
Classifier: Programming Language :: Python :: 3.8
Classifier: Programming Language :: Python :: 3.9
Classifier: Programming Language :: Python :: 3.10
Requires-Dist: anyio (>=3,<4)
Requires-Dist: transitions (>=0.8.6,<0.9.0)
